{
  "coverage": {
    "total_markers": 4,
    "with_views": 1,
    "with_subscribers": 0,
    "with_comments": 4
  },
  "videos_ranked_by_subs_per_1k": [
    {
      "video_id": "PARZJaJjsR4",
      "title": "Foxes hear tiny prey under snow",
      "category": "arctic",
      "story_format": "single_fact",
      "series": "Polar Survival",
      "views": 0,
      "subscribers_gained": 0,
      "subs_per_1k_views": 0.0,
      "comments_per_1k_views": 1000.0,
      "subscriber_conversion": {
        "score": 99,
        "state": "strong",
        "subscriber_probability": 0.141,
        "return_probability": 0.297,
        "comment_probability": 0.253,
        "robotic_title": {
          "risk": 0,
          "state": "clear",
          "hits": []
        },
        "reasons": [
          "hook_invites_return",
          "identity_cta",
          "debate_comment",
          "return_prompt",
          "series_identity"
        ],
        "confidence": {
          "confidence_score": 0.033,
          "sample_size": 1,
          "minimum_sample_size": 5,
          "data_quality": "inferred",
          "data_quality_score": 0.65,
          "recommendation_strength": "observe",
          "can_adjust_strategy": false,
          "bootstrap_multiplier": 0.274,
          "reasoning": "Combined 4 evidence source(s) with average confidence 0.03."
        },
        "reasoning": "Combined 4 evidence source(s) with average confidence 0.03."
      }
    },
    {
      "video_id": "jbJJ6Kvov7g",
      "title": "Cats use whiskers like built-in rulers",
      "category": "cats",
      "story_format": "body_superpower",
      "series": "Pet Secrets",
      "views": 0,
      "subscribers_gained": 0,
      "subs_per_1k_views": 0.0,
      "comments_per_1k_views": 1000.0,
      "subscriber_conversion": {
        "score": 86,
        "state": "strong",
        "subscriber_probability": 0.123,
        "return_probability": 0.261,
        "comment_probability": 0.223,
        "robotic_title": {
          "risk": 0,
          "state": "clear",
          "hits": []
        },
        "reasons": [
          "identity_cta",
          "debate_comment",
          "return_prompt",
          "series_identity"
        ],
        "confidence": {
          "confidence_score": 0.033,
          "sample_size": 1,
          "minimum_sample_size": 5,
          "data_quality": "inferred",
          "data_quality_score": 0.65,
          "recommendation_strength": "observe",
          "can_adjust_strategy": false,
          "bootstrap_multiplier": 0.274,
          "reasoning": "Combined 4 evidence source(s) with average confidence 0.03."
        },
        "reasoning": "Combined 4 evidence source(s) with average confidence 0.03."
      }
    },
    {
      "video_id": "zjSyMQQIUQ4",
      "title": "Earth systems use cloud patterns before they glow",
      "category": "earth_from_space",
      "story_format": "animal_intelligence",
      "series": "Animal Superpowers",
      "views": 0,
      "subscribers_gained": 0,
      "subs_per_1k_views": 0.0,
      "comments_per_1k_views": 1000.0,
      "subscriber_conversion": {
        "score": 99,
        "state": "strong",
        "subscriber_probability": 0.141,
        "return_probability": 0.297,
        "comment_probability": 0.253,
        "robotic_title": {
          "risk": 0,
          "state": "clear",
          "hits": []
        },
        "reasons": [
          "hook_invites_return",
          "identity_cta",
          "debate_comment",
          "return_prompt",
          "series_identity"
        ],
        "confidence": {
          "confidence_score": 0.033,
          "sample_size": 1,
          "minimum_sample_size": 5,
          "data_quality": "inferred",
          "data_quality_score": 0.65,
          "recommendation_strength": "observe",
          "can_adjust_strategy": false,
          "bootstrap_multiplier": 0.274,
          "reasoning": "Combined 4 evidence source(s) with average confidence 0.03."
        },
        "reasoning": "Combined 4 evidence source(s) with average confidence 0.03."
      }
    },
    {
      "video_id": "aVpHIzQnebw",
      "title": "Bears smell food from miles away",
      "category": "arctic",
      "story_format": "animal_intelligence",
      "series": "Polar Survival",
      "views": 5,
      "subscribers_gained": 0,
      "subs_per_1k_views": 0.0,
      "comments_per_1k_views": 200.0,
      "subscriber_conversion": {
        "score": 99,
        "state": "strong",
        "subscriber_probability": 0.141,
        "return_probability": 0.297,
        "comment_probability": 0.253,
        "robotic_title": {
          "risk": 0,
          "state": "clear",
          "hits": []
        },
        "reasons": [
          "hook_invites_return",
          "identity_cta",
          "debate_comment",
          "return_prompt",
          "series_identity"
        ],
        "confidence": {
          "confidence_score": 0.033,
          "sample_size": 1,
          "minimum_sample_size": 5,
          "data_quality": "inferred",
          "data_quality_score": 0.65,
          "recommendation_strength": "observe",
          "can_adjust_strategy": false,
          "bootstrap_multiplier": 0.274,
          "reasoning": "Combined 4 evidence source(s) with average confidence 0.03."
        },
        "reasoning": "Combined 4 evidence source(s) with average confidence 0.03."
      }
    }
  ],
  "category_subscriber_rates": {
    "arctic": 0.0,
    "cats": 0.0,
    "earth_from_space": 0.0
  },
  "format_subscriber_rates": {
    "single_fact": 0.0,
    "body_superpower": 0.0,
    "animal_intelligence": 0.0
  },
  "recurring_commenters": [
    {
      "author": "@wildbrief-e8o",
      "comments": 4
    }
  ],
  "subscriber_category_weights": {
    "arctic": 0.85,
    "cats": 0.85,
    "earth_from_space": 0.85
  }
}