{
  "counts": {
    "automation_safe": 9,
    "high": 1,
    "manual_review": 1,
    "total": 10,
    "urgent": 9
  },
  "free_only": true,
  "generated_at": "2026-06-29T08:34:19.159275+00:00",
  "items": [
    {
      "action_type": "pull_fresh_analytics",
      "age_hours": 20.409,
      "automation_safe": true,
      "category": "weather",
      "checkpoint_label": "1h",
      "checkpoint_state": "overdue",
      "current_views": 0,
      "due_at": "2026-06-28T13:09:45.477006+00:00",
      "free_only": true,
      "free_resource": "Committed analytics JSON, YouTube Studio free analytics, and GitHub Actions dashboard refresh.",
      "id": "fresh-upload:ZR7bZ3m550c:analytics_due:1h",
      "lane": "measurement",
      "manual_approval_required": false,
      "opening_retention_score": 90.0,
      "priority": "urgent",
      "recommended_action": "Run the analytics pull before making a creative decision. Check the 1h sample first.",
      "series": "Earth Engine",
      "state": "analytics_due",
      "target_views": 24,
      "title": "Lightning signals through lightning flash",
      "url": "https://www.youtube.com/shorts/ZR7bZ3m550c",
      "video_id": "ZR7bZ3m550c",
      "wait_until": "",
      "why": "The next checkpoint is due, but the system still needs a fresh measured sample."
    },
    {
      "action_type": "pull_fresh_analytics",
      "age_hours": 19.514,
      "automation_safe": true,
      "category": "chemistry",
      "checkpoint_label": "1h",
      "checkpoint_state": "overdue",
      "current_views": 0,
      "due_at": "2026-06-28T14:03:29.012385+00:00",
      "free_only": true,
      "free_resource": "Committed analytics JSON, YouTube Studio free analytics, and GitHub Actions dashboard refresh.",
      "id": "fresh-upload:W8pfsTzlVsk:analytics_due:1h",
      "lane": "measurement",
      "manual_approval_required": false,
      "opening_retention_score": 100.0,
      "priority": "urgent",
      "recommended_action": "Run the analytics pull before making a creative decision. Check the 1h sample first.",
      "series": "Nature Signals",
      "state": "analytics_due",
      "target_views": 24,
      "title": "Crystals grow by repeating one tiny pattern",
      "url": "https://www.youtube.com/shorts/W8pfsTzlVsk",
      "video_id": "W8pfsTzlVsk",
      "wait_until": "",
      "why": "The next checkpoint is due, but the system still needs a fresh measured sample."
    },
    {
      "action_type": "pull_fresh_analytics",
      "age_hours": 18.502,
      "automation_safe": true,
      "category": "plants",
      "checkpoint_label": "1h",
      "checkpoint_state": "overdue",
      "current_views": 0,
      "due_at": "2026-06-28T15:04:12.582437+00:00",
      "free_only": true,
      "free_resource": "Committed analytics JSON, YouTube Studio free analytics, and GitHub Actions dashboard refresh.",
      "id": "fresh-upload:JGE_LHh_GDQ:analytics_due:1h",
      "lane": "measurement",
      "manual_approval_required": false,
      "opening_retention_score": 96.0,
      "priority": "urgent",
      "recommended_action": "Run the analytics pull before making a creative decision. Check the 1h sample first.",
      "series": "Biology Brief",
      "state": "analytics_due",
      "target_views": 24,
      "title": "Tropical leaves turn sunlight into stored sugar",
      "url": "https://www.youtube.com/shorts/JGE_LHh_GDQ",
      "video_id": "JGE_LHh_GDQ",
      "wait_until": "",
      "why": "The next checkpoint is due, but the system still needs a fresh measured sample."
    },
    {
      "action_type": "pull_fresh_analytics",
      "age_hours": 16.414,
      "automation_safe": true,
      "category": "rivers",
      "checkpoint_label": "6h",
      "checkpoint_state": "overdue",
      "current_views": 2,
      "due_at": "2026-06-28T22:09:29.268170+00:00",
      "free_only": true,
      "free_resource": "Committed analytics JSON, YouTube Studio free analytics, and GitHub Actions dashboard refresh.",
      "id": "fresh-upload:xfOfa8OLwNw:analytics_due:6h",
      "lane": "measurement",
      "manual_approval_required": false,
      "opening_retention_score": 100.0,
      "priority": "urgent",
      "recommended_action": "Run the analytics pull before making a creative decision. Check the 6h sample first.",
      "series": "Earth Engine",
      "state": "analytics_due",
      "target_views": 105,
      "title": "River bends sort sand from larger stones",
      "url": "https://www.youtube.com/shorts/xfOfa8OLwNw",
      "video_id": "xfOfa8OLwNw",
      "wait_until": "",
      "why": "The next checkpoint is due, but the system still needs a fresh measured sample."
    },
    {
      "action_type": "pull_fresh_analytics",
      "age_hours": 11.232,
      "automation_safe": true,
      "category": "geology",
      "checkpoint_label": "1h",
      "checkpoint_state": "overdue",
      "current_views": 0,
      "due_at": "2026-06-28T22:20:25.711108+00:00",
      "free_only": true,
      "free_resource": "Committed analytics JSON, YouTube Studio free analytics, and GitHub Actions dashboard refresh.",
      "id": "fresh-upload:AdQTndo_VR4:analytics_due:1h",
      "lane": "measurement",
      "manual_approval_required": false,
      "opening_retention_score": 100.0,
      "priority": "urgent",
      "recommended_action": "Run the analytics pull before making a creative decision. Check the 1h sample first.",
      "series": "Earth Engine",
      "state": "analytics_due",
      "target_views": 24,
      "title": "Rock layers expose erosion in bare open hills",
      "url": "https://www.youtube.com/shorts/AdQTndo_VR4",
      "video_id": "AdQTndo_VR4",
      "wait_until": "",
      "why": "The next checkpoint is due, but the system still needs a fresh measured sample."
    },
    {
      "action_type": "pull_fresh_analytics",
      "age_hours": 15.116,
      "automation_safe": true,
      "category": "plants",
      "checkpoint_label": "6h",
      "checkpoint_state": "overdue",
      "current_views": 0,
      "due_at": "2026-06-28T23:27:21.477158+00:00",
      "free_only": true,
      "free_resource": "Committed analytics JSON, YouTube Studio free analytics, and GitHub Actions dashboard refresh.",
      "id": "fresh-upload:u5VrAUBYcKg:analytics_due:6h",
      "lane": "measurement",
      "manual_approval_required": false,
      "opening_retention_score": 72.0,
      "priority": "urgent",
      "recommended_action": "Run the analytics pull before making a creative decision. Check the 6h sample first.",
      "series": "Biology Brief",
      "state": "analytics_due",
      "target_views": 105,
      "title": "Flowers use trap hairs to count touches before snapping shut",
      "url": "https://www.youtube.com/shorts/u5VrAUBYcKg",
      "video_id": "u5VrAUBYcKg",
      "wait_until": "",
      "why": "The next checkpoint is due, but the system still needs a fresh measured sample."
    },
    {
      "action_type": "pull_fresh_analytics",
      "age_hours": 14.504,
      "automation_safe": true,
      "category": "plants",
      "checkpoint_label": "6h",
      "checkpoint_state": "overdue",
      "current_views": 0,
      "due_at": "2026-06-29T00:04:03.383685+00:00",
      "free_only": true,
      "free_resource": "Committed analytics JSON, YouTube Studio free analytics, and GitHub Actions dashboard refresh.",
      "id": "fresh-upload:uMBHm6tNXkg:analytics_due:6h",
      "lane": "measurement",
      "manual_approval_required": false,
      "opening_retention_score": 72.0,
      "priority": "urgent",
      "recommended_action": "Run the analytics pull before making a creative decision. Check the 6h sample first.",
      "series": "Biology Brief",
      "state": "analytics_due",
      "target_views": 105,
      "title": "Plants use trap hairs to count touches before snapping shut | Leaf surface",
      "url": "https://www.youtube.com/shorts/uMBHm6tNXkg",
      "video_id": "uMBHm6tNXkg",
      "wait_until": "",
      "why": "The next checkpoint is due, but the system still needs a fresh measured sample."
    },
    {
      "action_type": "pull_fresh_analytics",
      "age_hours": 13.461,
      "automation_safe": true,
      "category": "geology",
      "checkpoint_label": "6h",
      "checkpoint_state": "overdue",
      "current_views": 0,
      "due_at": "2026-06-29T01:06:37.895741+00:00",
      "free_only": true,
      "free_resource": "Committed analytics JSON, YouTube Studio free analytics, and GitHub Actions dashboard refresh.",
      "id": "fresh-upload:Jm1bnXNsYb0:analytics_due:6h",
      "lane": "measurement",
      "manual_approval_required": false,
      "opening_retention_score": 100.0,
      "priority": "urgent",
      "recommended_action": "Run the analytics pull before making a creative decision. Check the 6h sample first.",
      "series": "Earth Engine",
      "state": "analytics_due",
      "target_views": 105,
      "title": "This rock layer gives rock layers away",
      "url": "https://www.youtube.com/shorts/Jm1bnXNsYb0",
      "video_id": "Jm1bnXNsYb0",
      "wait_until": "",
      "why": "The next checkpoint is due, but the system still needs a fresh measured sample."
    },
    {
      "action_type": "pull_fresh_analytics",
      "age_hours": 12.53,
      "automation_safe": true,
      "category": "forests",
      "checkpoint_label": "6h",
      "checkpoint_state": "overdue",
      "current_views": 0,
      "due_at": "2026-06-29T02:02:29.373888+00:00",
      "free_only": true,
      "free_resource": "Committed analytics JSON, YouTube Studio free analytics, and GitHub Actions dashboard refresh.",
      "id": "fresh-upload:CWvl2EcQbGQ:analytics_due:6h",
      "lane": "measurement",
      "manual_approval_required": false,
      "opening_retention_score": 100.0,
      "priority": "urgent",
      "recommended_action": "Run the analytics pull before making a creative decision. Check the 6h sample first.",
      "series": "Hidden Network",
      "state": "analytics_due",
      "target_views": 105,
      "title": "Forest shade keeps soil moisture from leaving",
      "url": "https://www.youtube.com/shorts/CWvl2EcQbGQ",
      "video_id": "CWvl2EcQbGQ",
      "wait_until": "",
      "why": "The next checkpoint is due, but the system still needs a fresh measured sample."
    },
    {
      "action_type": "prepare_package_rescue",
      "age_hours": 17.44,
      "automation_safe": false,
      "category": "discoveries",
      "checkpoint_label": "24h",
      "checkpoint_state": "pending",
      "current_views": 0,
      "due_at": "2026-06-29T15:07:54.436158+00:00",
      "free_only": true,
      "free_resource": "Committed analytics JSON, YouTube Studio free analytics, and GitHub Actions dashboard refresh.",
      "id": "fresh-upload:WPRlhQVdM8k:repair_candidate:24h",
      "lane": "package_rescue",
      "manual_approval_required": true,
      "opening_retention_score": 100.0,
      "priority": "high",
      "recommended_action": "TITLE_AUTO_REPAIR_TRIGGER",
      "series": "Discovery Brief",
      "state": "repair_candidate",
      "target_views": 300,
      "title": "Fossils turn old bones into time clues",
      "url": "https://www.youtube.com/shorts/WPRlhQVdM8k",
      "video_id": "WPRlhQVdM8k",
      "wait_until": "",
      "why": "Observed velocity is weak enough to prepare a package intervention."
    }
  ],
  "source": "fresh_upload_watchlist",
  "source_generated_at": "2026-06-29T08:34:19.158146+00:00"
}
