{
  "approved": 15,
  "average_score": 84.65,
  "generated_at": "2026-07-02T12:10:46.751475+00:00",
  "pass_rate": 1.0,
  "rows": 15,
  "weak_openings": [],
  "worst_openings": [
    {
      "approved": true,
      "reasons": [],
      "score": 83.04,
      "source_title": "Lightning makes air explode into thunder",
      "title": "Lightning makes air explode into thunder",
      "title_issues": [],
      "video_id": "WbwdERQTz90"
    },
    {
      "approved": true,
      "reasons": [],
      "score": 83.76,
      "source_title": "Mountains reveal weather lines in snow",
      "title": "Mountains reveal weather lines in snow",
      "title_issues": [],
      "video_id": "or7TN0gMpWA"
    },
    {
      "approved": true,
      "reasons": [],
      "score": 84.84,
      "source_title": "Whales slap the surface to warn the pod",
      "title": "Whales slap the surface to warn the pod",
      "title_issues": [],
      "video_id": "vUB5OSOv218"
    },
    {
      "approved": true,
      "reasons": [],
      "score": 84.84,
      "source_title": "Forests make cooler air under the canopy",
      "title": "Forests make cooler air under the canopy",
      "title_issues": [],
      "video_id": "T0Wl3m_A7So"
    },
    {
      "approved": true,
      "reasons": [],
      "score": 84.84,
      "source_title": "Trees record wet years inside their rings",
      "title": "Trees record wet years inside their rings",
      "title_issues": [],
      "video_id": "Y-dGOykkcBM"
    },
    {
      "approved": true,
      "reasons": [],
      "score": 84.84,
      "source_title": "Snakes can detect warm prey in the dark",
      "title": "Snakes can detect warm prey in the dark",
      "title_issues": [],
      "video_id": "ytZXl-smi5Q"
    },
    {
      "approved": true,
      "reasons": [],
      "score": 84.84,
      "source_title": "Rivers sort mud and sand along each bank",
      "title": "Rivers sort mud and sand along each bank",
      "title_issues": [],
      "video_id": "Wi2VtQQ88X0"
    },
    {
      "approved": true,
      "reasons": [],
      "score": 84.84,
      "source_title": "Dogs read the world through scent maps",
      "title": "Dogs read the world through scent maps",
      "title_issues": [],
      "video_id": "peeCu1r3K0I"
    },
    {
      "approved": true,
      "reasons": [],
      "score": 84.84,
      "source_title": "Rock layers store ancient environments in stripes",
      "title": "Rock layers store ancient environments in stripes",
      "title_issues": [],
      "video_id": "FEAbi2e-yas"
    },
    {
      "approved": true,
      "reasons": [],
      "score": 84.84,
      "source_title": "Mushrooms release spores from hidden gills",
      "title": "Mushrooms release spores from hidden gills",
      "title_issues": [],
      "video_id": "LQPZdiuog_k"
    }
  ]
}
