{
  "comment_reply_short_candidates": [],
  "fresh_upload_actions": {
    "counts": {
      "automation_safe": 10,
      "high": 0,
      "manual_review": 0,
      "total": 10,
      "urgent": 9
    },
    "free_only": true,
    "generated_at": "2026-07-12T10:21:59.565181+00:00",
    "items": [
      {
        "action_type": "pull_fresh_analytics",
        "age_hours": 70.997,
        "automation_safe": true,
        "category": "arctic",
        "checkpoint_label": "1h",
        "checkpoint_state": "overdue",
        "current_views": 1,
        "due_at": "2026-07-09T12:22:11.609762+00:00",
        "free_only": true,
        "free_resource": "Committed analytics JSON, YouTube Studio free analytics, and GitHub Actions dashboard refresh.",
        "id": "fresh-upload:FauBvdeAeU8:analytics_due:1h",
        "lane": "measurement",
        "manual_approval_required": false,
        "opening_retention_score": 100.0,
        "priority": "urgent",
        "recommended_action": "Run the analytics pull before making a creative decision. Check the 1h sample first.",
        "series": "Polar Survival",
        "state": "analytics_due",
        "target_views": 24,
        "title": "Birds use ultraviolet vision before they change",
        "url": "https://www.youtube.com/shorts/FauBvdeAeU8",
        "video_id": "FauBvdeAeU8",
        "wait_until": "",
        "why": "The next checkpoint is due, but the system still needs a fresh measured sample."
      },
      {
        "action_type": "pull_fresh_analytics",
        "age_hours": 70.078,
        "automation_safe": true,
        "category": "plants",
        "checkpoint_label": "1h",
        "checkpoint_state": "overdue",
        "current_views": 0,
        "due_at": "2026-07-09T13:17:18.643262+00:00",
        "free_only": true,
        "free_resource": "Committed analytics JSON, YouTube Studio free analytics, and GitHub Actions dashboard refresh.",
        "id": "fresh-upload:jaUOVwj0oo4:analytics_due:1h",
        "lane": "measurement",
        "manual_approval_required": false,
        "opening_retention_score": 100.0,
        "priority": "urgent",
        "recommended_action": "Run the analytics pull before making a creative decision. Check the 1h sample first.",
        "series": "Biology Brief",
        "state": "analytics_due",
        "target_views": 24,
        "title": "Plants use trap hairs to count touches before closing",
        "url": "https://www.youtube.com/shorts/jaUOVwj0oo4",
        "video_id": "jaUOVwj0oo4",
        "wait_until": "",
        "why": "The next checkpoint is due, but the system still needs a fresh measured sample."
      },
      {
        "action_type": "pull_fresh_analytics",
        "age_hours": 68.289,
        "automation_safe": true,
        "category": "dogs",
        "checkpoint_label": "1h",
        "checkpoint_state": "overdue",
        "current_views": 3,
        "due_at": "2026-07-09T15:04:39.316623+00:00",
        "free_only": true,
        "free_resource": "Committed analytics JSON, YouTube Studio free analytics, and GitHub Actions dashboard refresh.",
        "id": "fresh-upload:8LrEpWspyK8:analytics_due:1h",
        "lane": "measurement",
        "manual_approval_required": false,
        "opening_retention_score": 100.0,
        "priority": "urgent",
        "recommended_action": "Run the analytics pull before making a creative decision. Check the 1h sample first.",
        "series": "Pet Secrets",
        "state": "analytics_due",
        "target_views": 24,
        "title": "Dogs use scent map before they smell",
        "url": "https://www.youtube.com/shorts/8LrEpWspyK8",
        "video_id": "8LrEpWspyK8",
        "wait_until": "",
        "why": "The next checkpoint is due, but the system still needs a fresh measured sample."
      },
      {
        "action_type": "pull_fresh_analytics",
        "age_hours": 63.394,
        "automation_safe": true,
        "category": "insects",
        "checkpoint_label": "1h",
        "checkpoint_state": "overdue",
        "current_views": 0,
        "due_at": "2026-07-09T19:58:19.695164+00:00",
        "free_only": true,
        "free_resource": "Committed analytics JSON, YouTube Studio free analytics, and GitHub Actions dashboard refresh.",
        "id": "fresh-upload:WCATjnYNSYo:analytics_due:1h",
        "lane": "measurement",
        "manual_approval_required": false,
        "opening_retention_score": 100.0,
        "priority": "urgent",
        "recommended_action": "Run the analytics pull before making a creative decision. Check the 1h sample first.",
        "series": "Tiny Worlds",
        "state": "analytics_due",
        "target_views": 24,
        "title": "Dragonflies use motion lock before they lock",
        "url": "https://www.youtube.com/shorts/WCATjnYNSYo",
        "video_id": "WCATjnYNSYo",
        "wait_until": "",
        "why": "The next checkpoint is due, but the system still needs a fresh measured sample."
      },
      {
        "action_type": "pull_fresh_analytics",
        "age_hours": 63.29,
        "automation_safe": true,
        "category": "nocturnal",
        "checkpoint_label": "1h",
        "checkpoint_state": "overdue",
        "current_views": 1,
        "due_at": "2026-07-09T20:04:33.771351+00:00",
        "free_only": true,
        "free_resource": "Committed analytics JSON, YouTube Studio free analytics, and GitHub Actions dashboard refresh.",
        "id": "fresh-upload:LdYL1w1rf0g:analytics_due:1h",
        "lane": "measurement",
        "manual_approval_required": false,
        "opening_retention_score": 100.0,
        "priority": "urgent",
        "recommended_action": "Run the analytics pull before making a creative decision. Check the 1h sample first.",
        "series": "Night Shift Nature",
        "state": "analytics_due",
        "target_views": 24,
        "title": "Foxes use snow hearing before they hunt",
        "url": "https://www.youtube.com/shorts/LdYL1w1rf0g",
        "video_id": "LdYL1w1rf0g",
        "wait_until": "",
        "why": "The next checkpoint is due, but the system still needs a fresh measured sample."
      },
      {
        "action_type": "pull_fresh_analytics",
        "age_hours": 62.293,
        "automation_safe": true,
        "category": "arctic",
        "checkpoint_label": "1h",
        "checkpoint_state": "overdue",
        "current_views": 2,
        "due_at": "2026-07-09T21:04:23.188358+00:00",
        "free_only": true,
        "free_resource": "Committed analytics JSON, YouTube Studio free analytics, and GitHub Actions dashboard refresh.",
        "id": "fresh-upload:XZIAdzI-njM:analytics_due:1h",
        "lane": "measurement",
        "manual_approval_required": false,
        "opening_retention_score": 94.0,
        "priority": "urgent",
        "recommended_action": "Run the analytics pull before making a creative decision. Check the 1h sample first.",
        "series": "Polar Survival",
        "state": "analytics_due",
        "target_views": 24,
        "title": "Seals can follow wakes with their whiskers",
        "url": "https://www.youtube.com/shorts/XZIAdzI-njM",
        "video_id": "XZIAdzI-njM",
        "wait_until": "",
        "why": "The next checkpoint is due, but the system still needs a fresh measured sample."
      },
      {
        "action_type": "pull_fresh_analytics",
        "age_hours": 61.321,
        "automation_safe": true,
        "category": "ocean",
        "checkpoint_label": "1h",
        "checkpoint_state": "overdue",
        "current_views": 2,
        "due_at": "2026-07-09T22:02:44.518371+00:00",
        "free_only": true,
        "free_resource": "Committed analytics JSON, YouTube Studio free analytics, and GitHub Actions dashboard refresh.",
        "id": "fresh-upload:xxal3t3p9K0:analytics_due:1h",
        "lane": "measurement",
        "manual_approval_required": false,
        "opening_retention_score": 94.0,
        "priority": "urgent",
        "recommended_action": "Run the analytics pull before making a creative decision. Check the 1h sample first.",
        "series": "Ocean Mysteries",
        "state": "analytics_due",
        "target_views": 24,
        "title": "Dolphins can call each other with signature whistles",
        "url": "https://www.youtube.com/shorts/xxal3t3p9K0",
        "video_id": "xxal3t3p9K0",
        "wait_until": "",
        "why": "The next checkpoint is due, but the system still needs a fresh measured sample."
      },
      {
        "action_type": "pull_fresh_analytics",
        "age_hours": 45.957,
        "automation_safe": true,
        "category": "insects",
        "checkpoint_label": "1h",
        "checkpoint_state": "overdue",
        "current_views": 1,
        "due_at": "2026-07-10T13:24:33.044741+00:00",
        "free_only": true,
        "free_resource": "Committed analytics JSON, YouTube Studio free analytics, and GitHub Actions dashboard refresh.",
        "id": "fresh-upload:VYPvTU9WqGE:analytics_due:1h",
        "lane": "measurement",
        "manual_approval_required": false,
        "opening_retention_score": 100.0,
        "priority": "urgent",
        "recommended_action": "Run the analytics pull before making a creative decision. Check the 1h sample first.",
        "series": "Tiny Worlds",
        "state": "analytics_due",
        "target_views": 24,
        "title": "Beetles steer after one star compass",
        "url": "https://www.youtube.com/shorts/VYPvTU9WqGE",
        "video_id": "VYPvTU9WqGE",
        "wait_until": "",
        "why": "The next checkpoint is due, but the system still needs a fresh measured sample."
      },
      {
        "action_type": "pull_fresh_analytics",
        "age_hours": 15.969,
        "automation_safe": true,
        "category": "microscopy",
        "checkpoint_label": "1h",
        "checkpoint_state": "overdue",
        "current_views": 0,
        "due_at": "2026-07-11T19:23:51.980992+00:00",
        "free_only": true,
        "free_resource": "Committed analytics JSON, YouTube Studio free analytics, and GitHub Actions dashboard refresh.",
        "id": "fresh-upload:PJXOHbhndt4:analytics_due:1h",
        "lane": "measurement",
        "manual_approval_required": false,
        "opening_retention_score": 72.0,
        "priority": "urgent",
        "recommended_action": "Run the analytics pull before making a creative decision. Check the 1h sample first.",
        "series": "Nature Signals",
        "state": "analytics_due",
        "target_views": 24,
        "title": "Cells copy instructions before splitting",
        "url": "https://www.youtube.com/shorts/PJXOHbhndt4",
        "video_id": "PJXOHbhndt4",
        "wait_until": "",
        "why": "The next checkpoint is due, but the system still needs a fresh measured sample."
      },
      {
        "action_type": "watch_next_checkpoint",
        "age_hours": 3.591,
        "automation_safe": true,
        "category": "geology",
        "checkpoint_label": "6h",
        "checkpoint_state": "pending",
        "current_views": 0,
        "due_at": "2026-07-12T12:46:30.181782+00:00",
        "free_only": true,
        "free_resource": "Committed analytics JSON, YouTube Studio free analytics, and GitHub Actions dashboard refresh.",
        "id": "fresh-upload:6Xko5TJwEdw:watch:6h",
        "lane": "observe",
        "manual_approval_required": false,
        "opening_retention_score": 100.0,
        "priority": "low",
        "recommended_action": "Keep observing through the next checkpoint.",
        "series": "Earth Engine",
        "state": "watch",
        "target_views": 105,
        "title": "Rock layers store ancient environments in stripes | Earth engine",
        "url": "https://www.youtube.com/shorts/6Xko5TJwEdw",
        "video_id": "6Xko5TJwEdw",
        "wait_until": "2026-07-12T12:46:30.181782+00:00",
        "why": "No intervention signal is strong enough yet."
      }
    ],
    "source": "fresh_upload_watchlist",
    "source_generated_at": "2026-07-12T10:21:59.564219+00:00"
  },
  "fresh_upload_watchlist": {
    "checkpoint_hours": [
      1,
      6,
      24
    ],
    "counts": {
      "analytics_due": 9,
      "awaiting_1h": 0,
      "high_priority": 9,
      "repair_candidates": 0,
      "tracked": 10
    },
    "generated_at": "2026-07-12T10:21:59.564219+00:00",
    "items": [
      {
        "action": "Keep observing through the next checkpoint.",
        "age_hours": 3.591,
        "category": "geology",
        "checkpoints": [
          {
            "delta_to_target": -24,
            "due_at": "2026-07-12T07:46:30.181782+00:00",
            "label": "1h",
            "source": "observed",
            "state": "observed",
            "target_views": 24,
            "views": 0
          },
          {
            "delta_to_target": 0,
            "due_at": "2026-07-12T12:46:30.181782+00:00",
            "label": "6h",
            "source": "estimated",
            "state": "pending",
            "target_views": 105,
            "views": 0
          },
          {
            "delta_to_target": 0,
            "due_at": "2026-07-13T06:46:30.181782+00:00",
            "label": "24h",
            "source": "estimated",
            "state": "pending",
            "target_views": 300,
            "views": 0
          }
        ],
        "current_views": 0,
        "hypothesis": "No intervention signal is strong enough yet.",
        "next_checkpoint": {
          "delta_to_target": 0,
          "due_at": "2026-07-12T12:46:30.181782+00:00",
          "label": "6h",
          "source": "estimated",
          "state": "pending",
          "target_views": 105,
          "views": 0
        },
        "opening_retention_score": 100.0,
        "opening_retention_state": "retention_ready",
        "priority": "low",
        "series": "Earth Engine",
        "state": "watch",
        "title": "Rock layers store ancient environments in stripes | Earth engine",
        "uploaded_at": "2026-07-12T06:46:30.181782+00:00",
        "url": "https://www.youtube.com/shorts/6Xko5TJwEdw",
        "video_id": "6Xko5TJwEdw",
        "views_per_hour": 0.0
      },
      {
        "action": "Run the analytics pull before making a creative decision.",
        "age_hours": 15.969,
        "category": "microscopy",
        "checkpoints": [
          {
            "delta_to_target": -24,
            "due_at": "2026-07-11T19:23:51.980992+00:00",
            "label": "1h",
            "source": "estimated",
            "state": "overdue",
            "target_views": 24,
            "views": 0
          },
          {
            "delta_to_target": -105,
            "due_at": "2026-07-12T00:23:51.980992+00:00",
            "label": "6h",
            "source": "estimated",
            "state": "overdue",
            "target_views": 105,
            "views": 0
          },
          {
            "delta_to_target": 0,
            "due_at": "2026-07-12T18:23:51.980992+00:00",
            "label": "24h",
            "source": "estimated",
            "state": "pending",
            "target_views": 300,
            "views": 0
          }
        ],
        "current_views": 0,
        "hypothesis": "The next checkpoint is due, but the system still needs a fresh measured sample.",
        "next_checkpoint": {
          "delta_to_target": -24,
          "due_at": "2026-07-11T19:23:51.980992+00:00",
          "label": "1h",
          "source": "estimated",
          "state": "overdue",
          "target_views": 24,
          "views": 0
        },
        "opening_retention_score": 72.0,
        "opening_retention_state": "needs_tightening",
        "priority": "high",
        "series": "Nature Signals",
        "state": "analytics_due",
        "title": "Cells copy instructions before splitting",
        "uploaded_at": "2026-07-11T18:23:51.980992+00:00",
        "url": "https://www.youtube.com/shorts/PJXOHbhndt4",
        "video_id": "PJXOHbhndt4",
        "views_per_hour": 0.0
      },
      {
        "action": "Run the analytics pull before making a creative decision.",
        "age_hours": 45.957,
        "category": "insects",
        "checkpoints": [
          {
            "delta_to_target": -24,
            "due_at": "2026-07-10T13:24:33.044741+00:00",
            "label": "1h",
            "source": "estimated",
            "state": "overdue",
            "target_views": 24,
            "views": 0
          },
          {
            "delta_to_target": -105,
            "due_at": "2026-07-10T18:24:33.044741+00:00",
            "label": "6h",
            "source": "estimated",
            "state": "overdue",
            "target_views": 105,
            "views": 0
          },
          {
            "delta_to_target": -300,
            "due_at": "2026-07-11T12:24:33.044741+00:00",
            "label": "24h",
            "source": "estimated",
            "state": "overdue",
            "target_views": 300,
            "views": 0
          }
        ],
        "current_views": 1,
        "hypothesis": "The next checkpoint is due, but the system still needs a fresh measured sample.",
        "next_checkpoint": {
          "delta_to_target": -24,
          "due_at": "2026-07-10T13:24:33.044741+00:00",
          "label": "1h",
          "source": "estimated",
          "state": "overdue",
          "target_views": 24,
          "views": 0
        },
        "opening_retention_score": 100.0,
        "opening_retention_state": "retention_ready",
        "priority": "high",
        "series": "Tiny Worlds",
        "state": "analytics_due",
        "title": "Beetles steer after one star compass",
        "uploaded_at": "2026-07-10T12:24:33.044741+00:00",
        "url": "https://www.youtube.com/shorts/VYPvTU9WqGE",
        "video_id": "VYPvTU9WqGE",
        "views_per_hour": 0.022
      },
      {
        "action": "Run the analytics pull before making a creative decision.",
        "age_hours": 61.321,
        "category": "ocean",
        "checkpoints": [
          {
            "delta_to_target": -24,
            "due_at": "2026-07-09T22:02:44.518371+00:00",
            "label": "1h",
            "source": "estimated",
            "state": "overdue",
            "target_views": 24,
            "views": 0
          },
          {
            "delta_to_target": -105,
            "due_at": "2026-07-10T03:02:44.518371+00:00",
            "label": "6h",
            "source": "estimated",
            "state": "overdue",
            "target_views": 105,
            "views": 0
          },
          {
            "delta_to_target": -300,
            "due_at": "2026-07-10T21:02:44.518371+00:00",
            "label": "24h",
            "source": "estimated",
            "state": "overdue",
            "target_views": 300,
            "views": 0
          }
        ],
        "current_views": 2,
        "hypothesis": "The next checkpoint is due, but the system still needs a fresh measured sample.",
        "next_checkpoint": {
          "delta_to_target": -24,
          "due_at": "2026-07-09T22:02:44.518371+00:00",
          "label": "1h",
          "source": "estimated",
          "state": "overdue",
          "target_views": 24,
          "views": 0
        },
        "opening_retention_score": 94.0,
        "opening_retention_state": "retention_ready",
        "priority": "high",
        "series": "Ocean Mysteries",
        "state": "analytics_due",
        "title": "Dolphins can call each other with signature whistles",
        "uploaded_at": "2026-07-09T21:02:44.518371+00:00",
        "url": "https://www.youtube.com/shorts/xxal3t3p9K0",
        "video_id": "xxal3t3p9K0",
        "views_per_hour": 0.033
      },
      {
        "action": "Run the analytics pull before making a creative decision.",
        "age_hours": 62.293,
        "category": "arctic",
        "checkpoints": [
          {
            "delta_to_target": -24,
            "due_at": "2026-07-09T21:04:23.188358+00:00",
            "label": "1h",
            "source": "estimated",
            "state": "overdue",
            "target_views": 24,
            "views": 0
          },
          {
            "delta_to_target": -105,
            "due_at": "2026-07-10T02:04:23.188358+00:00",
            "label": "6h",
            "source": "estimated",
            "state": "overdue",
            "target_views": 105,
            "views": 0
          },
          {
            "delta_to_target": -300,
            "due_at": "2026-07-10T20:04:23.188358+00:00",
            "label": "24h",
            "source": "estimated",
            "state": "overdue",
            "target_views": 300,
            "views": 0
          }
        ],
        "current_views": 2,
        "hypothesis": "The next checkpoint is due, but the system still needs a fresh measured sample.",
        "next_checkpoint": {
          "delta_to_target": -24,
          "due_at": "2026-07-09T21:04:23.188358+00:00",
          "label": "1h",
          "source": "estimated",
          "state": "overdue",
          "target_views": 24,
          "views": 0
        },
        "opening_retention_score": 94.0,
        "opening_retention_state": "retention_ready",
        "priority": "high",
        "series": "Polar Survival",
        "state": "analytics_due",
        "title": "Seals can follow wakes with their whiskers",
        "uploaded_at": "2026-07-09T20:04:23.188358+00:00",
        "url": "https://www.youtube.com/shorts/XZIAdzI-njM",
        "video_id": "XZIAdzI-njM",
        "views_per_hour": 0.032
      },
      {
        "action": "Run the analytics pull before making a creative decision.",
        "age_hours": 63.29,
        "category": "nocturnal",
        "checkpoints": [
          {
            "delta_to_target": -24,
            "due_at": "2026-07-09T20:04:33.771351+00:00",
            "label": "1h",
            "source": "estimated",
            "state": "overdue",
            "target_views": 24,
            "views": 0
          },
          {
            "delta_to_target": -105,
            "due_at": "2026-07-10T01:04:33.771351+00:00",
            "label": "6h",
            "source": "estimated",
            "state": "overdue",
            "target_views": 105,
            "views": 0
          },
          {
            "delta_to_target": -300,
            "due_at": "2026-07-10T19:04:33.771351+00:00",
            "label": "24h",
            "source": "estimated",
            "state": "overdue",
            "target_views": 300,
            "views": 0
          }
        ],
        "current_views": 1,
        "hypothesis": "The next checkpoint is due, but the system still needs a fresh measured sample.",
        "next_checkpoint": {
          "delta_to_target": -24,
          "due_at": "2026-07-09T20:04:33.771351+00:00",
          "label": "1h",
          "source": "estimated",
          "state": "overdue",
          "target_views": 24,
          "views": 0
        },
        "opening_retention_score": 100.0,
        "opening_retention_state": "retention_ready",
        "priority": "high",
        "series": "Night Shift Nature",
        "state": "analytics_due",
        "title": "Foxes use snow hearing before they hunt",
        "uploaded_at": "2026-07-09T19:04:33.771351+00:00",
        "url": "https://www.youtube.com/shorts/LdYL1w1rf0g",
        "video_id": "LdYL1w1rf0g",
        "views_per_hour": 0.016
      },
      {
        "action": "Run the analytics pull before making a creative decision.",
        "age_hours": 63.394,
        "category": "insects",
        "checkpoints": [
          {
            "delta_to_target": -24,
            "due_at": "2026-07-09T19:58:19.695164+00:00",
            "label": "1h",
            "source": "estimated",
            "state": "overdue",
            "target_views": 24,
            "views": 0
          },
          {
            "delta_to_target": -105,
            "due_at": "2026-07-10T00:58:19.695164+00:00",
            "label": "6h",
            "source": "estimated",
            "state": "overdue",
            "target_views": 105,
            "views": 0
          },
          {
            "delta_to_target": -300,
            "due_at": "2026-07-10T18:58:19.695164+00:00",
            "label": "24h",
            "source": "estimated",
            "state": "overdue",
            "target_views": 300,
            "views": 0
          }
        ],
        "current_views": 0,
        "hypothesis": "The next checkpoint is due, but the system still needs a fresh measured sample.",
        "next_checkpoint": {
          "delta_to_target": -24,
          "due_at": "2026-07-09T19:58:19.695164+00:00",
          "label": "1h",
          "source": "estimated",
          "state": "overdue",
          "target_views": 24,
          "views": 0
        },
        "opening_retention_score": 100.0,
        "opening_retention_state": "retention_ready",
        "priority": "high",
        "series": "Tiny Worlds",
        "state": "analytics_due",
        "title": "Dragonflies use motion lock before they lock",
        "uploaded_at": "2026-07-09T18:58:19.695164+00:00",
        "url": "https://www.youtube.com/shorts/WCATjnYNSYo",
        "video_id": "WCATjnYNSYo",
        "views_per_hour": 0.0
      },
      {
        "action": "Run the analytics pull before making a creative decision.",
        "age_hours": 68.289,
        "category": "dogs",
        "checkpoints": [
          {
            "delta_to_target": -24,
            "due_at": "2026-07-09T15:04:39.316623+00:00",
            "label": "1h",
            "source": "estimated",
            "state": "overdue",
            "target_views": 24,
            "views": 0
          },
          {
            "delta_to_target": -105,
            "due_at": "2026-07-09T20:04:39.316623+00:00",
            "label": "6h",
            "source": "estimated",
            "state": "overdue",
            "target_views": 105,
            "views": 0
          },
          {
            "delta_to_target": -299,
            "due_at": "2026-07-10T14:04:39.316623+00:00",
            "label": "24h",
            "source": "estimated",
            "state": "overdue",
            "target_views": 300,
            "views": 1
          }
        ],
        "current_views": 3,
        "hypothesis": "The next checkpoint is due, but the system still needs a fresh measured sample.",
        "next_checkpoint": {
          "delta_to_target": -24,
          "due_at": "2026-07-09T15:04:39.316623+00:00",
          "label": "1h",
          "source": "estimated",
          "state": "overdue",
          "target_views": 24,
          "views": 0
        },
        "opening_retention_score": 100.0,
        "opening_retention_state": "retention_ready",
        "priority": "high",
        "series": "Pet Secrets",
        "state": "analytics_due",
        "title": "Dogs use scent map before they smell",
        "uploaded_at": "2026-07-09T14:04:39.316623+00:00",
        "url": "https://www.youtube.com/shorts/8LrEpWspyK8",
        "video_id": "8LrEpWspyK8",
        "views_per_hour": 0.044
      },
      {
        "action": "Run the analytics pull before making a creative decision.",
        "age_hours": 70.078,
        "category": "plants",
        "checkpoints": [
          {
            "delta_to_target": -24,
            "due_at": "2026-07-09T13:17:18.643262+00:00",
            "label": "1h",
            "source": "estimated",
            "state": "overdue",
            "target_views": 24,
            "views": 0
          },
          {
            "delta_to_target": -105,
            "due_at": "2026-07-09T18:17:18.643262+00:00",
            "label": "6h",
            "source": "estimated",
            "state": "overdue",
            "target_views": 105,
            "views": 0
          },
          {
            "delta_to_target": -300,
            "due_at": "2026-07-10T12:17:18.643262+00:00",
            "label": "24h",
            "source": "estimated",
            "state": "overdue",
            "target_views": 300,
            "views": 0
          }
        ],
        "current_views": 0,
        "hypothesis": "The next checkpoint is due, but the system still needs a fresh measured sample.",
        "next_checkpoint": {
          "delta_to_target": -24,
          "due_at": "2026-07-09T13:17:18.643262+00:00",
          "label": "1h",
          "source": "estimated",
          "state": "overdue",
          "target_views": 24,
          "views": 0
        },
        "opening_retention_score": 100.0,
        "opening_retention_state": "retention_ready",
        "priority": "high",
        "series": "Biology Brief",
        "state": "analytics_due",
        "title": "Plants use trap hairs to count touches before closing",
        "uploaded_at": "2026-07-09T12:17:18.643262+00:00",
        "url": "https://www.youtube.com/shorts/jaUOVwj0oo4",
        "video_id": "jaUOVwj0oo4",
        "views_per_hour": 0.0
      },
      {
        "action": "Run the analytics pull before making a creative decision.",
        "age_hours": 70.997,
        "category": "arctic",
        "checkpoints": [
          {
            "delta_to_target": -24,
            "due_at": "2026-07-09T12:22:11.609762+00:00",
            "label": "1h",
            "source": "estimated",
            "state": "overdue",
            "target_views": 24,
            "views": 0
          },
          {
            "delta_to_target": -105,
            "due_at": "2026-07-09T17:22:11.609762+00:00",
            "label": "6h",
            "source": "estimated",
            "state": "overdue",
            "target_views": 105,
            "views": 0
          },
          {
            "delta_to_target": -300,
            "due_at": "2026-07-10T11:22:11.609762+00:00",
            "label": "24h",
            "source": "estimated",
            "state": "overdue",
            "target_views": 300,
            "views": 0
          }
        ],
        "current_views": 1,
        "hypothesis": "The next checkpoint is due, but the system still needs a fresh measured sample.",
        "next_checkpoint": {
          "delta_to_target": -24,
          "due_at": "2026-07-09T12:22:11.609762+00:00",
          "label": "1h",
          "source": "estimated",
          "state": "overdue",
          "target_views": 24,
          "views": 0
        },
        "opening_retention_score": 100.0,
        "opening_retention_state": "retention_ready",
        "priority": "high",
        "series": "Polar Survival",
        "state": "analytics_due",
        "title": "Birds use ultraviolet vision before they change",
        "uploaded_at": "2026-07-09T11:22:11.609762+00:00",
        "url": "https://www.youtube.com/shorts/FauBvdeAeU8",
        "video_id": "FauBvdeAeU8",
        "views_per_hour": 0.014
      }
    ],
    "targets": {
      "1h": 24,
      "24h": 300,
      "6h": 105
    },
    "window_hours": 72
  },
  "generated_at": "2026-07-12T10:21:59.565273+00:00",
  "playlist_sequence_notes": [
    "Place each new Short after the closest same-series winner.",
    "Use related video manually in Studio when official automation is unavailable."
  ],
  "related_video_recommendations": [
    {
      "recommendation": {
        "reason": "same series/category/format session bridge",
        "score": 85.0,
        "title": "Seals track fish trails with whiskers",
        "url": "https://www.youtube.com/shorts/GO7SG1fM1y0",
        "video_id": "GO7SG1fM1y0"
      },
      "source_title": "Seals can follow wakes with their whiskers",
      "source_video_id": "XZIAdzI-njM"
    },
    {
      "recommendation": {
        "reason": "same series/category/format session bridge",
        "score": 65.0,
        "title": "Whales slap the surface to warn the pod",
        "url": "https://www.youtube.com/shorts/vUB5OSOv218",
        "video_id": "vUB5OSOv218"
      },
      "source_title": "Dolphins can call each other with signature whistles",
      "source_video_id": "xxal3t3p9K0"
    },
    {
      "recommendation": {
        "reason": "same series/category/format session bridge",
        "score": 85.0,
        "title": "Beetles can steer by the Milky Way",
        "url": "https://www.youtube.com/shorts/zkOPZdHY4i0",
        "video_id": "zkOPZdHY4i0"
      },
      "source_title": "Beetles steer after one star compass",
      "source_video_id": "VYPvTU9WqGE"
    },
    {
      "recommendation": {
        "reason": "same series/category/format session bridge",
        "score": 30.0,
        "title": "Crystals grow by repeating one tiny pattern",
        "url": "https://www.youtube.com/shorts/NxfTBrgi_ns",
        "video_id": "NxfTBrgi_ns"
      },
      "source_title": "Cells copy instructions before splitting",
      "source_video_id": "PJXOHbhndt4"
    },
    {
      "recommendation": {
        "reason": "same series/category/format session bridge",
        "score": 85.0,
        "title": "Rock layers store ancient environments in stripes",
        "url": "https://www.youtube.com/shorts/FEAbi2e-yas",
        "video_id": "FEAbi2e-yas"
      },
      "source_title": "Rock layers store ancient environments in stripes | Earth engine",
      "source_video_id": "6Xko5TJwEdw"
    }
  ],
  "sequel_opportunities": [
    {
      "prompt": "Make a sequel with a new subject but the same payoff shape: Seals can follow wakes with their whiskers",
      "title": "Seals can follow wakes with their whiskers",
      "video_id": "XZIAdzI-njM"
    },
    {
      "prompt": "Make a sequel with a new subject but the same payoff shape: Dolphins can call each other with signature whistles",
      "title": "Dolphins can call each other with signature whistles",
      "video_id": "xxal3t3p9K0"
    },
    {
      "prompt": "Make a sequel with a new subject but the same payoff shape: Beetles steer after one star compass",
      "title": "Beetles steer after one star compass",
      "video_id": "VYPvTU9WqGE"
    },
    {
      "prompt": "Make a sequel with a new subject but the same payoff shape: Cells copy instructions before splitting",
      "title": "Cells copy instructions before splitting",
      "video_id": "PJXOHbhndt4"
    },
    {
      "prompt": "Make a sequel with a new subject but the same payoff shape: Rock layers store ancient environments in stripes | Earth engine",
      "title": "Rock layers store ancient environments in stripes | Earth engine",
      "video_id": "6Xko5TJwEdw"
    }
  ],
  "session_graph": {
    "action_score_threshold": 55,
    "coverage": 0.95,
    "edges": 20,
    "nodes": 95,
    "target_reuse_limit": 2
  }
}
