{
  "total": 1000,
  "reasons": {
    "duplicate_title": 526,
    "off_topic_visual": 202,
    "queue_score_reject": 175,
    "duplicate_script": 155,
    "duplicate_angle": 124,
    "copy_subject_mismatch": 121,
    "script_hook_mismatch": 78,
    "script_subject_mismatch": 62,
    "missing_action_word": 51,
    "rights_guard_person_manual_review": 49,
    "subject_not_immediately_clear": 46,
    "no_action_promise": 43,
    "missing_visible_cue": 27,
    "subject_not_clear": 26,
    "title_shape_weak": 21,
    "title_needs_stronger_shape": 21,
    "non_animal_body_language": 21,
    "script_length_risk": 19,
    "script_word_loop": 11,
    "bad_plural_verb": 6,
    "missing_visual_cue": 2,
    "script does not expose enough concrete visual detail": 2,
    "generic_creator_language": 1,
    "thumbnail_text_not_scannable": 1,
    "thumbnail_not_2_4_words": 1
  },
  "stages": {
    "queue_prune": 467,
    "queue_prune_final": 358,
    "queue_repair": 175
  },
  "latest": [
    {
      "story_id": "45c11ea2aa792a7f",
      "stage": "queue_prune_final",
      "reasons": [
        "duplicate_title",
        "duplicate_script",
        "duplicate_angle"
      ],
      "title": "Lions use dark ear marks to guide cubs",
      "category": "wildlife",
      "script_key": "lions have dark ear marks cubs can follow watch the backs of the ears because those dark marks can stand out when a lion moves through grass for cubs that contrast helps track the adult ahead the detail is small but the pride depends on staying together would you spot it",
      "angle_key": "lions|follow|ear marks|wildlife",
      "source_url": "https://www.pexels.com/video/sea-lion-resting-on-pristine-beach-shoreline-36985340/",
      "pexels_video_id": "36985340",
      "source_clip_id": "pexels:45c11ea2aa792a7f",
      "recorded_at": "2026-06-24T01:52:44.079493+00:00",
      "rewrite_attempted": true,
      "rewrite_applied": true
    },
    {
      "story_id": "dac50e1974da0e3e",
      "stage": "queue_prune_final",
      "reasons": [
        "script_subject_mismatch",
        "copy_subject_mismatch"
      ],
      "title": "Storm clouds reveal weather from above the clouds",
      "category": "earth_from_space",
      "script_key": "storm clouds look different when seen from above watch the cloud tops because the upper shape shows where air is rising flattening or spreading out from above weather becomes a texture map instead of a ceiling which above cloud clue should we compare next",
      "angle_key": "storm|reveal|cloud tops|earth_from_space",
      "source_url": "https://www.pexels.com/video/aerial-view-of-scenic-landscape-from-airplane-35763906/",
      "pexels_video_id": "35763906",
      "source_clip_id": "pexels:dac50e1974da0e3e",
      "recorded_at": "2026-06-24T01:52:44.094543+00:00",
      "rewrite_attempted": true,
      "rewrite_applied": true
    },
    {
      "story_id": "01f2bb6e69bc35a2",
      "stage": "queue_prune_final",
      "reasons": [
        "duplicate_title"
      ],
      "title": "Storm clouds reveal a storm's heat engine",
      "category": "earth_from_space",
      "script_key": "storm clouds show where a storm is feeding watch the spiral shape because warm ocean air rises near the center and releases heat as clouds build rotation organizes that energy into bands from above the storm is not random it is an engine which satellite clue next",
      "angle_key": "storm|build|clouds|earth_from_space",
      "source_url": "https://www.pexels.com/video/majestic-snow-capped-mountain-range-aerial-view-36085334/",
      "pexels_video_id": "36085334",
      "source_clip_id": "pexels:01f2bb6e69bc35a2",
      "recorded_at": "2026-06-24T01:52:44.109635+00:00",
      "rewrite_attempted": true,
      "rewrite_applied": true
    },
    {
      "story_id": "4929b70c979eb002",
      "stage": "queue_prune_final",
      "reasons": [
        "duplicate_title"
      ],
      "title": "Storm clouds reveal a storm's heat engine",
      "category": "earth_from_space",
      "script_key": "storm clouds show where a storm is feeding watch the spiral shape because warm ocean air rises near the center and releases heat as clouds build rotation organizes that energy into bands from above the storm is not random it is an engine which satellite clue next",
      "angle_key": "storm|build|clouds|earth_from_space",
      "source_url": "https://www.pexels.com/video/aerial-cityscape-under-dramatic-dark-clouds-32410697/",
      "pexels_video_id": "32410697",
      "source_clip_id": "pexels:4929b70c979eb002",
      "recorded_at": "2026-06-24T01:52:44.124474+00:00",
      "rewrite_attempted": true,
      "rewrite_applied": true
    },
    {
      "story_id": "6a9ce515930b99d0",
      "stage": "queue_prune_final",
      "reasons": [
        "duplicate_title",
        "duplicate_script",
        "duplicate_angle"
      ],
      "title": "Fossils turn old bones into time clues",
      "category": "discoveries",
      "script_key": "fossils can preserve a clue from deep time watch the shape in the rock because fossils form when buried remains leave mineral records behind the original body is gone but the pattern can reveal age habitat and behavior which ancient clue should we read next",
      "angle_key": "rock|form|pattern|discoveries",
      "source_url": "https://www.pexels.com/video/robbe-aquarium-biarritz-17836410/",
      "pexels_video_id": "17836410",
      "source_clip_id": "pexels:6a9ce515930b99d0",
      "recorded_at": "2026-06-24T01:52:44.139488+00:00",
      "rewrite_attempted": true,
      "rewrite_applied": true
    },
    {
      "story_id": "423fd78b24101fb3",
      "stage": "queue_prune_final",
      "reasons": [
        "duplicate_title",
        "duplicate_script",
        "duplicate_angle"
      ],
      "title": "Magnets make invisible fields visible",
      "category": "physics",
      "script_key": "magnets can show a hidden force map watch the filings line up because each tiny piece becomes a small magnet in the field together they trace the direction of the force around the magnet the pattern is physics drawing itself which force next",
      "angle_key": "physics|make|field lines|physics",
      "source_url": "https://www.pexels.com/video/a-white-rug-with-a-wooden-bench-in-the-middle-9472812/",
      "pexels_video_id": "9472812",
      "source_clip_id": "pexels:423fd78b24101fb3",
      "recorded_at": "2026-06-24T01:52:44.154308+00:00",
      "rewrite_attempted": true,
      "rewrite_applied": true
    },
    {
      "story_id": "9e373174a27691e4",
      "stage": "queue_prune_final",
      "reasons": [
        "duplicate_title",
        "duplicate_script",
        "duplicate_angle"
      ],
      "title": "Magnets make invisible fields visible",
      "category": "physics",
      "script_key": "magnets can show a hidden force map watch the filings line up because each tiny piece becomes a small magnet in the field together they trace the direction of the force around the magnet the pattern is physics drawing itself which force next",
      "angle_key": "physics|make|field lines|physics",
      "source_url": "https://www.pexels.com/video/stop-motion-video-of-a-man-using-a-vacuum-cleaner-while-floating-on-air-4159112/",
      "pexels_video_id": "4159112",
      "source_clip_id": "pexels:9e373174a27691e4",
      "recorded_at": "2026-06-24T01:52:44.168892+00:00",
      "rewrite_attempted": true,
      "rewrite_applied": true
    },
    {
      "story_id": "12f9acb4d30ff96a",
      "stage": "queue_prune",
      "reasons": [
        "off_topic_visual"
      ],
      "title": "Tropical forests hide a second sky above the trees",
      "category": "earth_from_space",
      "script_key": "look up in the rainforest and you ll see a second sky just moss and leaves stuck to branches like tiny umbrellas that s how trees drink through their bark without wasting a drop because sunlight never reaches the ground the canopy steals it all from above",
      "angle_key": "forests|hide|canopy|earth_from_space",
      "source_url": "https://www.pexels.com/video/aerial-view-over-lush-green-tropical-forest-31119984/",
      "pexels_video_id": "31119984",
      "source_clip_id": "pexels:12f9acb4d30ff96a",
      "recorded_at": "2026-06-24T01:57:14.794188+00:00",
      "rewrite_attempted": false,
      "rewrite_applied": false
    },
    {
      "story_id": "fc795d71f22f53be",
      "stage": "queue_prune",
      "reasons": [
        "script_subject_mismatch",
        "copy_subject_mismatch",
        "duplicate_title"
      ],
      "title": "Snakes smell the air with their tongues",
      "category": "reptiles",
      "script_key": "snakes sample the air with a tongue flick watch the tongue flick because it collects scent particles and sends them to a special organ in the mouth that helps snakes track prey mates and danger without needing a loud chase the air is information would you notice the trail",
      "angle_key": "snakes|sample|tongue smell|reptiles",
      "source_url": "https://www.pexels.com/video/close-up-of-green-iguana-in-tropical-habitat-36707601/",
      "pexels_video_id": "36707601",
      "source_clip_id": "pexels:fc795d71f22f53be",
      "recorded_at": "2026-06-24T01:57:14.810912+00:00",
      "rewrite_attempted": true,
      "rewrite_applied": true
    },
    {
      "story_id": "ca39e3b3dadc07e4",
      "stage": "queue_repair",
      "reasons": [
        "queue_score_reject"
      ],
      "title": "Dogs read human pointing surprisingly well",
      "category": "dogs",
      "script_key": "dogs can follow a human point fast watch the eyes check the person because dogs are unusually good at using human gestures that skill helps them cooperate with us before any command gets repeated the small glance is social intelligence not random obedience what dog skill should come next",
      "angle_key": "dogs|follow|human pointing|dogs",
      "source_url": "https://www.pexels.com/video/a-woman-hugging-a-dog-on-the-floor-16168331/",
      "pexels_video_id": "16168331",
      "source_clip_id": "pexels:ca39e3b3dadc07e4",
      "recorded_at": "2026-06-24T01:57:14.826024+00:00",
      "rewrite_attempted": true,
      "rewrite_applied": true
    },
    {
      "story_id": "e50dd9112ba319e6",
      "stage": "queue_prune",
      "reasons": [
        "duplicate_title",
        "duplicate_script",
        "duplicate_angle"
      ],
      "title": "Lions hunt better when the pride coordinates",
      "category": "wildlife",
      "script_key": "lions turn hunting into a team problem watch the spacing before the chase because lions can use different positions in a group hunt one animal pressures while another blocks the escape path the power is not just muscle which predator tactic should we break down next",
      "angle_key": "lions|escape|pride plan|wildlife",
      "source_url": "https://www.pexels.com/video/sea-lion-at-zoo-resting-by-a-pool-35308280/",
      "pexels_video_id": "35308280",
      "source_clip_id": "pexels:e50dd9112ba319e6",
      "recorded_at": "2026-06-24T01:57:14.841240+00:00",
      "rewrite_attempted": true,
      "rewrite_applied": true
    },
    {
      "story_id": "d7881340be790b55",
      "stage": "queue_prune_final",
      "reasons": [
        "duplicate_script",
        "duplicate_angle"
      ],
      "title": "Cats use grooming to reset their scent map",
      "category": "cats",
      "script_key": "cats use grooming to reset their scent map watch the tongue and paw movements because grooming spreads familiar scent across the coat that can help a cat settle after a tense moment and keep the fur ready for the next move the cleanup is also a signal which pet behavior should we decode next",
      "angle_key": "cats|signal|grooming signal|cats",
      "source_url": "https://www.pexels.com/video/street-cat-17592108/",
      "pexels_video_id": "17592108",
      "source_clip_id": "pexels:d7881340be790b55",
      "recorded_at": "2026-06-24T01:57:14.855988+00:00",
      "rewrite_attempted": true,
      "rewrite_applied": true
    },
    {
      "story_id": "886d2adaebc576c2",
      "stage": "queue_repair",
      "reasons": [
        "subject_not_immediately_clear",
        "no_action_promise",
        "missing_action_word",
        "queue_score_reject"
      ],
      "title": "The moon keeps one face turned toward Earth",
      "category": "space",
      "script_key": "the moon shows us one face for a reason watch the moon s position because its rotation and orbit are locked together it spins once in about the same time it circles earth so the same side keeps facing us that is synchronized motion not stillness which orbit clue next",
      "angle_key": "earth|show|face|space",
      "source_url": "https://www.pexels.com/video/close-up-video-of-a-ice-putting-in-the-water-8676913/",
      "pexels_video_id": "8676913",
      "source_clip_id": "pexels:886d2adaebc576c2",
      "recorded_at": "2026-06-24T02:00:33.821133+00:00",
      "rewrite_attempted": true,
      "rewrite_applied": true
    },
    {
      "story_id": "90123d66d2156433",
      "stage": "queue_prune",
      "reasons": [
        "off_topic_visual"
      ],
      "title": "Eastern screech owl hides in plain sight",
      "category": "trees",
      "script_key": "that face isn t staring at you notice the ear tufts blend into the bark like broken twigs screech owls don t spin their heads 360 their eyes are fixed that s why they tilt their whole bodies side to side like a bobblehead did you ever think they were just bad at turning around",
      "angle_key": "owl|survive|eyes|trees",
      "source_url": "https://www.pexels.com/video/eastern-screech-owl-in-tree-hollow-34925087/",
      "pexels_video_id": "34925087",
      "source_clip_id": "pexels:90123d66d2156433",
      "recorded_at": "2026-06-24T02:00:33.838219+00:00",
      "rewrite_attempted": false,
      "rewrite_applied": false
    },
    {
      "story_id": "1aacabfd0ece7b9e",
      "stage": "queue_prune",
      "reasons": [
        "off_topic_visual"
      ],
      "title": "Butterflies don’t drink with their mouths",
      "category": "plants",
      "script_key": "they taste with their feet not their mouths watch this one twice its feet just tapped the leaf like it s texting that s why it can taste flowers before it even lands what s the wildest way you ve ever tasted something without your mouth",
      "angle_key": "butterflies|close|feet|plants",
      "source_url": "https://www.pexels.com/video/close-up-of-a-butterfly-on-a-leaf-33667549/",
      "pexels_video_id": "33667549",
      "source_clip_id": "pexels:1aacabfd0ece7b9e",
      "recorded_at": "2026-06-24T02:00:33.854234+00:00",
      "rewrite_attempted": false,
      "rewrite_applied": false
    },
    {
      "story_id": "b28f3023140535c3",
      "stage": "queue_repair",
      "reasons": [
        "queue_score_reject"
      ],
      "title": "Birds see ultraviolet patterns we miss",
      "category": "arctic",
      "script_key": "birds see colors humans cannot see watch the feathers and eyes because many birds see ultraviolet detail hidden from us that extra color can help with mates food and navigation the same scene is richer to them than it is to us which bird fact next",
      "angle_key": "birds|see|ultraviolet|arctic",
      "source_url": "https://www.pexels.com/video/bird-catches-fish-in-calm-ocean-waters-28097182/",
      "pexels_video_id": "28097182",
      "source_clip_id": "pexels:b28f3023140535c3",
      "recorded_at": "2026-06-24T02:00:33.869734+00:00",
      "rewrite_attempted": true,
      "rewrite_applied": true
    },
    {
      "story_id": "434b07134e3ecfad",
      "stage": "queue_prune",
      "reasons": [
        "rights_guard_person_manual_review"
      ],
      "title": "Dogs read human pointing surprisingly well",
      "category": "dogs",
      "script_key": "dogs can follow a human point fast watch the eyes check the person because dogs are unusually good at using human gestures that skill helps them cooperate with us before any command gets repeated the small glance is social intelligence not random obedience what dog skill should come next",
      "angle_key": "dogs|follow|human pointing|dogs",
      "source_url": "https://www.pexels.com/video/woman-petting-a-dog-6568518/",
      "pexels_video_id": "6568518",
      "source_clip_id": "pexels:434b07134e3ecfad",
      "recorded_at": "2026-06-24T02:00:33.884745+00:00",
      "rewrite_attempted": true,
      "rewrite_applied": true
    },
    {
      "story_id": "5694a4ae2450652f",
      "stage": "queue_prune",
      "reasons": [
        "copy_subject_mismatch",
        "duplicate_title"
      ],
      "title": "Coral reefs are cities built by tiny animals",
      "category": "ecosystems",
      "script_key": "coral reefs are built by tiny living builders watch the reef texture because coral animals build hard skeletons that stack into habitat fish algae and countless small creatures then use that structure like a city the color sits on top of engineering which habitat next",
      "angle_key": "coral|build|reef city|ecosystems",
      "source_url": "https://www.pexels.com/video/a-fisherman-bringing-bucket-and-fishing-rod-8065127/",
      "pexels_video_id": "8065127",
      "source_clip_id": "pexels:5694a4ae2450652f",
      "recorded_at": "2026-06-24T02:00:33.900237+00:00",
      "rewrite_attempted": true,
      "rewrite_applied": true
    },
    {
      "story_id": "14150e89a5092e0c",
      "stage": "queue_prune",
      "reasons": [
        "duplicate_title"
      ],
      "title": "Monkeys wash food when grit gets annoying",
      "category": "primates",
      "script_key": "monkeys can change habits to solve small problems watch the hands near the food because some monkeys learn useful routines from their group washing or handling food differently can remove grit and make eating easier the habit spreads because it works which primate trick should come next",
      "angle_key": "monkeys|trick|hands|primates",
      "source_url": "https://www.pexels.com/video/monkeys-observing-nature-on-stone-pathway-35495118/",
      "pexels_video_id": "35495118",
      "source_clip_id": "pexels:14150e89a5092e0c",
      "recorded_at": "2026-06-24T02:00:33.916003+00:00",
      "rewrite_attempted": true,
      "rewrite_applied": true
    },
    {
      "story_id": "3e2ba5e7c80236d8",
      "stage": "queue_repair",
      "reasons": [
        "queue_score_reject"
      ],
      "title": "Dolphins use signature whistles like names",
      "category": "ocean",
      "script_key": "dolphins can call each other with signature whistles watch the group spacing because dolphins use sound to keep track of individuals in open water a signature whistle works like a personal label helping the pod reconnect when visibility drops ocean social life is loud which sound should we decode next",
      "angle_key": "dolphins|call|signature whistle|ocean",
      "source_url": "https://www.pexels.com/video/dolphin-swimming-in-blue-aquarium-11042821/",
      "pexels_video_id": "11042821",
      "source_clip_id": "pexels:3e2ba5e7c80236d8",
      "recorded_at": "2026-06-24T02:00:33.930620+00:00",
      "rewrite_attempted": true,
      "rewrite_applied": true
    },
    {
      "story_id": "307f5194e13c5f66",
      "stage": "queue_prune_final",
      "reasons": [
        "duplicate_title"
      ],
      "title": "Horses point their ears toward what matters",
      "category": "farm",
      "script_key": "horses show attention with their ears watch the ears before the body moves because each ear can turn toward a sound or animal the horse is tracking that small shift shows where attention is going before the next step the ears are a radar dish not decoration would you spot it",
      "angle_key": "horses|point|sound|farm",
      "source_url": "https://www.pexels.com/video/a-video-of-grazing-horses-6198905/",
      "pexels_video_id": "6198905",
      "source_clip_id": "pexels:307f5194e13c5f66",
      "recorded_at": "2026-06-24T02:00:33.946769+00:00",
      "rewrite_attempted": true,
      "rewrite_applied": true
    },
    {
      "story_id": "c65b850798fa5c0f",
      "stage": "queue_prune_final",
      "reasons": [
        "script_subject_mismatch",
        "copy_subject_mismatch"
      ],
      "title": "Deer can aim each ear toward danger",
      "category": "forests",
      "script_key": "deer can aim each ear toward danger watch the ears first because deer can turn them to sample sound from different directions that quick listening check helps them decide whether to freeze flee or keep feeding one quiet second tells the whole body what to do would you freeze",
      "angle_key": "deer|aim|sound radar|forests",
      "source_url": "https://www.pexels.com/video/a-red-mushroom-in-the-forest-18812521/",
      "pexels_video_id": "18812521",
      "source_clip_id": "pexels:c65b850798fa5c0f",
      "recorded_at": "2026-06-24T02:00:33.961902+00:00",
      "rewrite_attempted": true,
      "rewrite_applied": true
    },
    {
      "story_id": "d0520e6419d352c8",
      "stage": "queue_prune_final",
      "reasons": [
        "duplicate_script",
        "duplicate_angle"
      ],
      "title": "Cats use grooming to reset their scent map",
      "category": "cats",
      "script_key": "cats use grooming to reset their scent map watch the tongue and paw movements because grooming spreads familiar scent across the coat that can help a cat settle after a tense moment and keep the fur ready for the next move the cleanup is also a signal which pet behavior should we decode next",
      "angle_key": "cats|signal|grooming signal|cats",
      "source_url": "https://www.pexels.com/video/snow-covered-pallas-s-cat-resting-in-winter-enclosure-35681363/",
      "pexels_video_id": "35681363",
      "source_clip_id": "pexels:d0520e6419d352c8",
      "recorded_at": "2026-06-24T02:00:33.976761+00:00",
      "rewrite_attempted": true,
      "rewrite_applied": true
    },
    {
      "story_id": "8f8a089d6d6618a8",
      "stage": "queue_prune_final",
      "reasons": [
        "duplicate_title"
      ],
      "title": "Rock layers store ancient environments in stripes",
      "category": "geology",
      "script_key": "rock layers are time stamps made of stone watch the stripe pattern because each layer can mark a different setting river mud ocean floor windblown sand or volcanic ash stack enough layers and the cliff becomes a timeline which rock clue should we read next",
      "angle_key": "rock|store|rock layers|geology",
      "source_url": "https://www.pexels.com/video/close-up-video-of-a-rock-7830751/",
      "pexels_video_id": "7830751",
      "source_clip_id": "pexels:8f8a089d6d6618a8",
      "recorded_at": "2026-06-24T02:00:34.003611+00:00",
      "rewrite_attempted": true,
      "rewrite_applied": true
    },
    {
      "story_id": "477eb4ca09527c9b",
      "stage": "queue_prune_final",
      "reasons": [
        "duplicate_title"
      ],
      "title": "Rock layers store ancient environments in stripes",
      "category": "geology",
      "script_key": "rock layers are time stamps made of stone watch the stripe pattern because each layer can mark a different setting river mud ocean floor windblown sand or volcanic ash stack enough layers and the cliff becomes a timeline which rock clue should we read next",
      "angle_key": "rock|store|rock layers|geology",
      "source_url": "https://www.pexels.com/video/colorado-days-26862208/",
      "pexels_video_id": "26862208",
      "source_clip_id": "pexels:477eb4ca09527c9b",
      "recorded_at": "2026-06-24T02:00:34.019415+00:00",
      "rewrite_attempted": true,
      "rewrite_applied": true
    }
  ]
}